README.md
pyproject.toml
setup.py
octostar/__init__.py
octostar/client.py
octostar/errors.py
octostar/py.typed
octostar/types.py
octostar/api/__init__.py
octostar/api/default/__init__.py
octostar/api/default/post_api_octostar_workspace_data_api_zip_import.py
octostar/api/jobs/__init__.py
octostar/api/jobs/delete_job.py
octostar/api/jobs/execute_new_job.py
octostar/api/jobs/get_job_logs.py
octostar/api/jobs/get_job_progress.py
octostar/api/jobs/get_jobs_url.py
octostar/api/jobs/list_jobs.py
octostar/api/jobs/list_jobs_children.py
octostar/api/jobs/list_pods.py
octostar/api/jobs/post_api_octostar_jobs_deploy_workspace_os_entity_uid.py
octostar/api/jobs/set_job_progress.py
octostar/api/metadata/__init__.py
octostar/api/metadata/get_whoami.py
octostar/api/notifications/__init__.py
octostar/api/notifications/delete_stream.py
octostar/api/notifications/fake_wso_event.py
octostar/api/notifications/get_subscriptions.py
octostar/api/notifications/publish_notification.py
octostar/api/notifications/pull_events_from_stream.py
octostar/api/notifications/push_event_to_stream.py
octostar/api/notifications/subscribe.py
octostar/api/notifications/toast.py
octostar/api/notifications/unsubscribe.py
octostar/api/ontology/__init__.py
octostar/api/ontology/fetch_ontology_data.py
octostar/api/ontology/get_ontologies.py
octostar/api/ontology/query.py
octostar/api/secrets/__init__.py
octostar/api/secrets/delete_secret.py
octostar/api/secrets/get_secret.py
octostar/api/secrets/write_secret.py
octostar/api/url_storage/__init__.py
octostar/api/url_storage/delete_object.py
octostar/api/url_storage/get_object.py
octostar/api/url_storage/post_object.py
octostar/api/url_storage/post_object_with_id.py
octostar/api/watchers/__init__.py
octostar/api/watchers/get_watcher_intents.py
octostar/api/watchers/get_watcher_jobs.py
octostar/api/workspace_data/__init__.py
octostar/api/workspace_data/copy.py
octostar/api/workspace_data/create_workspace.py
octostar/api/workspace_data/delete_concept_records.py
octostar_python_client.egg-info/PKG-INFO
octostar_python_client.egg-info/SOURCES.txt
octostar_python_client.egg-info/dependency_links.txt
octostar_python_client.egg-info/requires.txt
octostar_python_client.egg-info/top_level.txt