Metadata-Version: 2.1
Name: octostar-python-client
Version: 1.0.0
Summary: A client library for accessing Octostar API
Requires-Python: >=3.8, <4
